client/__init__.py
client/client.py
client/client/__init__.py
client/client/add_contact.py
client/client/client_ui.py
client/client/core.py
client/client/database.py
client/client/del_contact.py
client/client/gui.py
client/client/start_dialog.py
client/common/__init__.py
client/common/decos.py
client/common/descriptors.py
client/common/errors.py
client/common/metaclasses.py
client/common/utils.py
client/common/variables.py
client/logs/__init__.py
client/logs/config_client_log.py
oleup_msg_client-0.0.1.dist-info/METADATA
oleup_msg_client-0.0.1.dist-info/WHEEL
oleup_msg_client-0.0.1.dist-info/top_level.txt
oleup_msg_client-0.0.1.dist-info/RECORD
