Metadata-Version: 2.1
Name: oleup-msg-client
Version: 0.0.1
Summary: message_client
Home-page: UNKNOWN
Author: Ole_Up
Author-email: oleup@yandex.ru
License: UNKNOWN
Platform: UNKNOWN
Requires-Dist: PyQt5
Requires-Dist: pycryptodome
Requires-Dist: pycryptodomex
Requires-Dist: sqlalchemy
